{
  "qq_number": "3384043236",
  "group_number": "1080217114",
  "updated_at": "2026-05-31T18:09:58+00:00",
  "skins": [
    {
      "name": "四月是你的谎言",
      "file": "雨天の四月是你的谎言.bdi",
      "thumb": "雨天の四月是你的谎言.bdi_py_26_light_thumb.png",
      "full": "雨天の四月是你的谎言.bdi_py_26_light.png"
    },
    {
      "name": "雨天の虚拟绯偶",
      "file": "虚拟绯偶.bdi",
      "thumb": "虚拟绯偶.bdi_py_26_light_thumb.png",
      "full": "虚拟绯偶.bdi_py_26_light.png"
    },
    {
      "name": "未寄情书",
      "file": "雨天の未寄情书.bdi",
      "thumb": "雨天の未寄情书.bdi_py_26_light_thumb.png",
      "full": "雨天の未寄情书.bdi_py_26_light.png"
    },
    {
      "name": "雨天の櫻雨紛紛",
      "file": "雨天の櫻雨紛紛.bdi",
      "thumb": "雨天の櫻雨紛紛.bdi_py_26_light_thumb.png",
      "full": "雨天の櫻雨紛紛.bdi_py_26_light.png"
    },
    {
      "name": "未闻啵名",
      "file": "未闻啵名.bdi",
      "thumb": "未闻啵名.bdi_py_26_light_thumb.png",
      "full": "未闻啵名.bdi_py_26_light.png"
    },
    {
      "name": "乐妍贴纸底包1",
      "file": "雨天の幸福降临优爱掌心.bdi",
      "thumb": "雨天の幸福降临优爱掌心.bdi_py_26_light_thumb.png",
      "full": "雨天の幸福降临优爱掌心.bdi_py_26_light.png"
    },
    {
      "name": "A.R.O.N.A",
      "file": "雨天のARONA.bdi",
      "thumb": "雨天のARONA.bdi_py_26_light_thumb.png",
      "full": "雨天のARONA.bdi_py_26_light.png"
    },
    {
      "name": "元气少女缘结神",
      "file": "雨天の元气少女缘结神.bdi",
      "thumb": "雨天の元气少女缘结神.bdi_py_26_light_thumb.png",
      "full": "雨天の元气少女缘结神.bdi_py_26_light.png"
    },
    {
      "name": "雨天の虚拟绯偶",
      "file": "虚拟绯偶.bds",
      "thumb": "虚拟绯偶.bds_py_26_light_thumb.png",
      "full": "虚拟绯偶.bds_py_26_light.png"
    },
    {
      "name": "未寄情书",
      "file": "雨天の未寄情书.bds",
      "thumb": "雨天の未寄情书.bds_py_26_light_thumb.png",
      "full": "雨天の未寄情书.bds_py_26_light.png"
    },
    {
      "name": "雨天の四月是你的谎言",
      "file": "雨天の四月是你的谎言.bds",
      "thumb": "雨天の四月是你的谎言.bds_py_26_light_thumb.png",
      "full": "雨天の四月是你的谎言.bds_py_26_light.png"
    },
    {
      "name": "未闻啵名",
      "file": "未闻啵名.bds",
      "thumb": "未闻啵名.bds_py_26_light_thumb.png",
      "full": "未闻啵名.bds_py_26_light.png"
    },
    {
      "name": "幸福降临优爱掌心",
      "file": "雨天の幸福降临优爱掌心.bds",
      "thumb": "雨天の幸福降临优爱掌心.bds_py_26_light_thumb.png",
      "full": "雨天の幸福降临优爱掌心.bds_py_26_light.png"
    },
    {
      "name": "A.R.O.N.A",
      "file": "雨天のARONA.bds",
      "thumb": "雨天のARONA.bds_py_26_light_thumb.png",
      "full": "雨天のARONA.bds_py_26_light.png"
    },
    {
      "name": "雨天の櫻雨紛紛",
      "file": "雨天の櫻雨紛紛.bds",
      "thumb": "雨天の櫻雨紛紛.bds_py_26_light_thumb.png",
      "full": "雨天の櫻雨紛紛.bds_py_26_light.png"
    },
    {
      "name": "雨天の元气少女缘结神",
      "file": "雨天の元气少女缘结神.bds",
      "thumb": "雨天の元气少女缘结神.bds_py_26_light_thumb.png",
      "full": "雨天の元气少女缘结神.bds_py_26_light.png"
    },
    {
      "name": "心の小羊缎带手礼浅色版闷闷",
      "file": "心の小羊缎带手礼浅色版闷闷.bdi",
      "thumb": "心の小羊缎带手礼浅色版闷闷.bdi_py_26_light_thumb.png",
      "full": "心の小羊缎带手礼浅色版闷闷.bdi_py_26_light_thumb.png"
    }
  ]
}